{
  "المؤتمر": "SB62 - الدورة الثانية والستون للهيئتين الفرعيتين",
  "الجلسات": 4,
  "إجراءات_معلّقة": 3,
  "الإجراءات": [
    {
      "المعرّف": "ACT-001",
      "الإجراء": "تقديم ورقة موقف العراق على المادة 6.2",
      "المسؤول": "المفاوض 1",
      "الموعد": "2026-06-01",
      "الأولوية": "عالية",
      "الحالة": "معلّق",
      "الجلسة": "SBSTA-62-1"
    },
    {
      "المعرّف": "ACT-002",
      "الإجراء": "مراجعة وثيقة FCCC/SBSTA/2026/L.1 وإعداد التعليقات",
      "المسؤول": "المفاوض 2",
      "الموعد": "2026-06-02",
      "الأولوية": "عالية",
      "الحالة": "معلّق",
      "الجلسة": "SBSTA-62-1"
    },
    {
      "المعرّف": "ACT-003",
      "الإجراء": "التنسيق مع الوفد الأردني على ورقة الدول العربية",
      "المسؤول": "رئيس الوفد",
      "الموعد": "2026-06-01",
      "الأولوية": "متوسطة",
      "الحالة": "معلّق",
      "الجلسة": "AG-1"
    }
  ]
}